napari_filaments/__init__.py
napari_filaments/_consts.py
napari_filaments/_optimizer.py
napari_filaments/_spline.py
napari_filaments/_types.py
napari_filaments/core.py
napari_filaments/napari.yaml
napari_filaments/_himena/__init__.py
napari_filaments/_himena/_commands.py
napari_filaments/_himena/_subwidgets.py
napari_filaments/_himena/_widget.py
napari_filaments/_icon/__init__.py
napari_filaments/_icon/clip_l.png
napari_filaments/_icon/clip_r.png
napari_filaments/_icon/del.png
napari_filaments/_icon/erf2.png
napari_filaments/_icon/erf_l.png
napari_filaments/_icon/erf_r.png
napari_filaments/_icon/ext_l.png
napari_filaments/_icon/ext_r.png
napari_filaments/_icon/extfit_l.png
napari_filaments/_icon/extfit_r.png
napari_filaments/_icon/fit.png
napari_filaments/_icon/redo.png
napari_filaments/_icon/undo.png
napari_filaments/_napari/__init__.py
napari_filaments/_napari/_custom_layers.py
napari_filaments/_napari/_subwidgets.py
napari_filaments/_napari/_table_stack.py
napari_filaments/_napari/_widget.py
napari_filaments/_tests/__init__.py
napari_filaments/_tests/image.tif
napari_filaments/_tests/test_optimizer.py
napari_filaments/_tests/test_widget.py
napari_filaments/_tests/_roi/RoiSet.zip
napari_filaments/_tests/_roi/line.roi
napari_filaments/_tests/_roi/path.roi
napari_filaments-0.4.0.dist-info/METADATA
napari_filaments-0.4.0.dist-info/WHEEL
napari_filaments-0.4.0.dist-info/entry_points.txt
napari_filaments-0.4.0.dist-info/licenses/LICENSE
napari_filaments-0.4.0.dist-info/RECORD
