Metadata-Version: 2.4
Name: napari-filaments
Version: 0.4.0
Summary: Plugin for filament analysis
Project-URL: Bug Tracker, https://github.com/hanjinliu/napari-filaments/issues
Project-URL: Documentation, https://github.com/hanjinliu/napari-filaments#README.md
Project-URL: Homepage, https://github.com/hanjinliu/napari-filaments
Project-URL: Source Code, https://github.com/hanjinliu/napari-filaments
Project-URL: User Support, https://github.com/hanjinliu/napari-filaments/issues
Author-email: Hanjin Liu <liuhanjin.sc@gmail.com>
License-Expression: BSD-3-Clause
License-File: LICENSE
Classifier: Development Status :: 2 - Pre-Alpha
Classifier: Framework :: napari
Classifier: Intended Audience :: Developers
Classifier: License :: OSI Approved :: BSD License
Classifier: Operating System :: OS Independent
Classifier: Programming Language :: Python
Classifier: Programming Language :: Python :: 3
Classifier: Programming Language :: Python :: 3 :: Only
Classifier: Topic :: Software Development :: Testing
Requires-Python: >=3.9
Requires-Dist: macro-kit
Requires-Dist: magic-class>=0.7.6
Requires-Dist: magicgui
Requires-Dist: matplotlib
Requires-Dist: numpy
Requires-Dist: pandas
Requires-Dist: psygnal
Requires-Dist: scipy
Provides-Extra: himena
Requires-Dist: himena; extra == 'himena'
Provides-Extra: napari
Requires-Dist: napari; extra == 'napari'
Provides-Extra: testing
Requires-Dist: napari; extra == 'testing'
Requires-Dist: pyqt5; extra == 'testing'
Requires-Dist: pytest; extra == 'testing'
Requires-Dist: pytest-cov; extra == 'testing'
Requires-Dist: pytest-qt; extra == 'testing'
Requires-Dist: roifile; extra == 'testing'
Requires-Dist: tox; extra == 'testing'
